arke/__about__.py
arke/__init__.py
arke/_version.py
arke/gateway/__init__.py
arke/gateway/errors.py
arke/gateway/manager.py
arke/gateway/shard.py
arke/http/__init__.py
arke/http/auth.py
arke/http/client.py
arke/http/errors.py
arke/http/ratelimit.py
arke/http/route.py
arke/internal/json.py
arke/internal/ratelimit.py
arke/utils/__init__.py
arke/utils/dispatcher.py
arke_discord-0.1.2.dist-info/METADATA
arke_discord-0.1.2.dist-info/WHEEL
arke_discord-0.1.2.dist-info/licenses/LICENSE
arke_discord-0.1.2.dist-info/RECORD
