Metadata-Version: 2.1
Name: arke-discord
Version: 0.1.2
Summary: Python Discord API Wrapper made from the ground up.
Author-Email: Emre Terzioglu <emreterzioglu49@gmail.com>
License: MIT
Classifier: Development Status :: 2 - Pre-Alpha
Classifier: License :: OSI Approved :: MIT License
Classifier: Operating System :: OS Independent
Classifier: Programming Language :: Python :: 3 :: Only
Classifier: Programming Language :: Python :: 3.10
Classifier: Programming Language :: Python :: 3.11
Classifier: Framework :: AsyncIO
Classifier: Topic :: Internet
Classifier: Topic :: Internet :: WWW/HTTP
Classifier: Typing :: Typed
Project-URL: Homepage, https://github.com/EmreTech/arke
Project-URL: Bug tracker, https://github.com/EmreTech/arke/issues
Requires-Python: >=3.10
Requires-Dist: aiohttp<4.0,>=3.8.0
Requires-Dist: discord-typings<1.0,>=0.6.0
